synth_forc/__init__.py
synth_forc/logger.py
synth_forc/plotter_threads.py
synth_forc/settings.py
synth_forc/synthforc_db.py
synth_forc/temporary_directory_space.py
synth_forc/cli/__init__.py
synth_forc/cli/forc.py
synth_forc/cli/response.py
synth_forc/gui/__init__.py
synth_forc/gui/main.py
synth_forc/gui/main_window.py
synth_forc/gui/save_dialog.py
synth_forc/gui/settings_dialog.py
synth_forc/gui/spinner.py
synth_forc/plotting/__init__.py
synth_forc/plotting/forc.py
synth_forc/plotting/forc_loops.py
synth_forc/plotting/log_normal.py
synth_forc/qt/__init__.py
synth_forc/qt/main_window.py
synth_forc/qt/save_dialog.py
synth_forc/qt/settings_dialog.py
synth_forc-0.1.2.dist-info/LICENCE.txt
synth_forc-0.1.2.dist-info/METADATA
synth_forc-0.1.2.dist-info/WHEEL
synth_forc-0.1.2.dist-info/entry_points.txt
synth_forc-0.1.2.dist-info/top_level.txt
synth_forc-0.1.2.dist-info/RECORD
